nsgi/__init__.py
nsgi/application.py
nsgi/logger.py
nsgi/models.py
nsgi/responses.py
nsgi/route.py
nsgi/runner.py
nsgi/plugins/__init__.py
nsgi/plugins/discord_bot.py
nsgi/plugins/ratelimit.py
nsgi-1.0.4.dist-info/LICENSE
nsgi-1.0.4.dist-info/METADATA
nsgi-1.0.4.dist-info/WHEEL
nsgi-1.0.4.dist-info/top_level.txt
nsgi-1.0.4.dist-info/RECORD
